Workbook

Sheet Summary
A1: Issue log summary (updates automatically when Status / Priority are changed)
A3: Status | B3: All | C3: High | D3: Medium | E3: Low
A4: Resolved (business confirmed) | B4: =COUNTIF('Issue Log'!$H$2:$H$94,A4) -> 26 | C4: =COUNTIFS('Issue Log'!$H$2:$H$94,A4,'Issue Log'!$J$2:$J$94,"High") -> 10 | D4: =COUNTIFS('Issue Log'!$H$2:$H$94,A4,'Issue Log'!$J$2:$J$94,"Medium") -> 13 | E4: =COUNTIFS('Issue Log'!$H$2:$H$94,A4,'Issue Log'!$J$2:$J$94,"Low") -> 3
A5: Handled in model | B5: =COUNTIF('Issue Log'!$H$2:$H$94,A5) -> 30 | C5: =COUNTIFS('Issue Log'!$H$2:$H$94,A5,'Issue Log'!$J$2:$J$94,"High") -> 5 | D5: =COUNTIFS('Issue Log'!$H$2:$H$94,A5,'Issue Log'!$J$2:$J$94,"Medium") -> 9 | E5: =COUNTIFS('Issue Log'!$H$2:$H$94,A5,'Issue Log'!$J$2:$J$94,"Low") -> 16
A6: Open - business | B6: =COUNTIF('Issue Log'!$H$2:$H$94,A6) -> 23 | C6: =COUNTIFS('Issue Log'!$H$2:$H$94,A6,'Issue Log'!$J$2:$J$94,"High") -> 7 | D6: =COUNTIFS('Issue Log'!$H$2:$H$94,A6,'Issue Log'!$J$2:$J$94,"Medium") -> 11 | E6: =COUNTIFS('Issue Log'!$H$2:$H$94,A6,'Issue Log'!$J$2:$J$94,"Low") -> 5
A7: Open - ERP team | B7: =COUNTIF('Issue Log'!$H$2:$H$94,A7) -> 8 | C7: =COUNTIFS('Issue Log'!$H$2:$H$94,A7,'Issue Log'!$J$2:$J$94,"High") -> 2 | D7: =COUNTIFS('Issue Log'!$H$2:$H$94,A7,'Issue Log'!$J$2:$J$94,"Medium") -> 4 | E7: =COUNTIFS('Issue Log'!$H$2:$H$94,A7,'Issue Log'!$J$2:$J$94,"Low") -> 2
A8: Open - verify with full data | B8: =COUNTIF('Issue Log'!$H$2:$H$94,A8) -> 3 | C8: =COUNTIFS('Issue Log'!$H$2:$H$94,A8,'Issue Log'!$J$2:$J$94,"High") -> 0 | D8: =COUNTIFS('Issue Log'!$H$2:$H$94,A8,'Issue Log'!$J$2:$J$94,"Medium") -> 1 | E8: =COUNTIFS('Issue Log'!$H$2:$H$94,A8,'Issue Log'!$J$2:$J$94,"Low") -> 2
A9: Assumed - please confirm | B9: =COUNTIF('Issue Log'!$H$2:$H$94,A9) -> 3 | C9: =COUNTIFS('Issue Log'!$H$2:$H$94,A9,'Issue Log'!$J$2:$J$94,"High") -> 0 | D9: =COUNTIFS('Issue Log'!$H$2:$H$94,A9,'Issue Log'!$J$2:$J$94,"Medium") -> 1 | E9: =COUNTIFS('Issue Log'!$H$2:$H$94,A9,'Issue Log'!$J$2:$J$94,"Low") -> 2
A10: Total | B10: =SUM(B4:B9) -> 93 | C10: =SUM(C4:C9) -> 24 | D10: =SUM(D4:D9) -> 39 | E10: =SUM(E4:E9) -> 30
A12: Check: total equals number of issues | B12: =IF(B10=COUNTA('Issue Log'!$A$2:$A$94),"OK","MISMATCH - a status value is misspelled") -> OK
A14: Open by owner | B14: Open items
A15: Business (you) | B15: =COUNTIFS('Issue Log'!$K$2:$K$94,A15,'Issue Log'!$H$2:$H$94,"Open*")+COUNTIFS('Issue Log'!$K$2:$K$94,A15,'Issue Log'!$H$2:$H$94,"Assumed*") -> 27
A16: ERP team | B16: =COUNTIFS('Issue Log'!$K$2:$K$94,A16,'Issue Log'!$H$2:$H$94,"Open*")+COUNTIFS('Issue Log'!$K$2:$K$94,A16,'Issue Log'!$H$2:$H$94,"Assumed*") -> 8
A17: Data team | B17: =COUNTIFS('Issue Log'!$K$2:$K$94,A17,'Issue Log'!$H$2:$H$94,"Open*")+COUNTIFS('Issue Log'!$K$2:$K$94,A17,'Issue Log'!$H$2:$H$94,"Assumed*") -> 2

Sheet Issue Log
A1: ID | B1: Area | C1: Source file | D1: Issue found | E1: Evidence | F1: Impact if not handled | G1: How the model handles it | H1: Status | I1: Answer / resolution | J1: Priority | K1: Owner
A2: D-001 | B2: Scope | C2: All sample files | D2: Sample files cover Apr-Sep 2026, not from Apr 2025 as planned | E2: Sales, transfers, PO, inventory samples all start 1-Apr-2026 | F2: Forecasting needs a full year incl. festive season | G2: Prototype period set to 1-Apr-2025..15-Sep-2026 | H2: Resolved (business confirmed) | I2: Samples only; full ~1.5-year data will be provided | J2: High | K2: Business (you)
A3: D-002 | B3: Scope | C3: All sources | D3: Full 1.5-year data pull not yet received for any source | E3: Only samples loaded so far | F3: Nothing can be loaded for real yet | G3: Loaders will be built against the sample layouts | H3: Open - business | J3: High | K3: Business (you)
A4: D-003 | B4: Scope | C4: Return files | D4: Return files run past the 15-Sep cut-off | E4: 133 retail return rows and 40 domestic return rows dated 16-22 Sep | F4: Returns counted without their matching sales period | G4: Cut-off stored as a setting (meta.pipeline_setting); rows after it excluded at staging | H4: Resolved (business confirmed) | I4: Use data only up to 15-Sep-2026 | J4: Medium | K4: Data team
A5: D-004 | B5: Scope | C5: Inventory | D5: Inventory history cannot be pulled: only today's snapshot | E5: Business confirmed; ERP has no historical stock report | F5: Stock trends impossible for past dates; each unsaved day is lost | G5: Daily snapshot fact; history approximated by rolling back through movements | H5: Open - ERP team | I5: Start saving the ERP, Blinkit and Instamart stock reports daily into a dated folder | J5: High | K5: ERP team
A6: D-005 | B6: Scope | C6: Blinkit / Instamart | D6: Blinkit return sheet (and Instamart's, if any) not received | E6: Business confirmed returns are in a separate sheet | F6: Quick-commerce returns missing; net sales overstated | G6: Will be registered as a new source when received | H6: Open - business | I6: Will be shared when available | J6: Medium | K6: Business (you)
A7: D-006 | B7: Scope | C7: Franchise / SIS | D7: No sell-out data from franchise and SIS stores | E7: Only sell-in invoices exist in the ERP | F7: Stock AI reads stock that later comes back as demand | G7: Demand for these channels uses net sales after returns until sell-out arrives | H7: Open - business | I7: Business will work out how to extract it | J7: Medium | K7: Business (you)
A8: D-007 | B8: Scope | C8: Blinkit / Instamart | D8: No Blinkit or Instamart invoices found in the ERP for Apr-Sep 2026 | E8: No Kiranakart/Swiggy names in Domestic Sales; no QC channel in Retail Sales; yet Kiranakart appears in returns and Blinkit locations hold ERP stock | F8: Quick-commerce revenue may be missing from ERP-based revenue | G8: Revenue = ERP invoices only; platform sell-out stored separately for demand | H8: Open - business | I8: Partly answered: QC is sale-or-return. Still unclear where QC invoices are raised in the ERP | J8: High | K8: Business (you)
A9: D-008 | B9: Scope | C9: WMS dispatch | D9: Dispatch sample was pasted as text, not shared as a file | E9: Rows pasted in chat, dated Apr 2025 | F9: Cannot test joins (e.g. invoice match rate) until a real export arrives | G9: Model designed from the pasted columns | H9: Open - verify with full data | J9: Low | K9: Business (you)
A10: D-009 | B10: Retail sales | C10: Retail Sales | D10: CHANNELNAME is the billing location, not the sales channel | E10: Values like '08 Jaipur Branch', '24 FBA WH - AMD2' | F10: Channel reports would show warehouses instead of channels | G10: Channel from CONTACTNAME; CHANNELNAME used as location | H10: Resolved (business confirmed) | I10: Use CONTACTNAME for channel | J10: High | K10: Data team
A11: D-010 | B11: Retail sales | C11: Retail Sales | D11: Channel unclear for some payment modes (COD, Snapmint, FNP, ICICI bank, Advance) | E11: COD = 3,947 lines / Rs 52.9 lakh; Snapmint 80; FNP 19; ICICI 18; Advance 3 | F11: Channel split wrong on the dashboard | G11: Resolved through CONTACTNAME: COD and Snapmint are all under Shopify_Customer (website) | H11: Resolved (business confirmed) | I11: Use CONTACTNAME | J11: High | K11: Data team
A12: D-011 | B12: Retail sales | C12: Retail Sales | D12: PRODASSESSABLEVALUE INCLUDES GST despite its name; PRODDOCVALUE is the excl-GST value | E12: PRODDOCVALUE + GST = PRODASSESSABLEVALUE on every product line; e.g. MRP 850 - disc 17 = 833 incl GST; 705.93 excl | F12: Retail revenue overstated by the GST amount | G12: Headline value = PRODDOCVALUE; load fails if the relationship stops holding | H12: Resolved (business confirmed) | I12: Headline sales = excluding GST | J12: High | K12: Data team
A13: D-012 | B13: Retail sales | C13: Retail Sales | D13: PRODDOCVALUE is blank on charge lines (SHIPPING R, Gifting) | E13: Only non-product lines fail the GST check | F13: Charge revenue lost if PRODDOCVALUE used blindly | G13: Excl-GST value for these lines = PRODASSESSABLEVALUE minus GST; kept as CHARGE item type | H13: Handled in model | J13: Low | K13: Data team
A14: D-013 | B14: Retail sales | C14: Retail Sales | D14: Non-product codes appear as invoice lines | E14: SHIPPING R, carry bags COCB04-06, Gifting, packaging codes | F14: Product sales and SKU counts polluted | G14: Every code kept in dim_product with item_type; SKU analysis uses TRADING only | H14: Handled in model | J14: Medium | K14: Data team
A15: D-014 | B15: Retail sales | C15: Retail Sales | D15: Bare contact 'Dileep Essentials Pvt Ltd' on retail invoices | E15: 39 lines, Rs 2 lakh; paid via 'DEPL HYD Store A/c', 'DEPL Jaipur - C-Scheme Exp.' | F15: Mis-classified as a D2C sale | G15: Classified as export through Dileep | H15: Resolved (business confirmed) | I15: All are exports through Dileep | J15: Medium | K15: Data team
A16: D-015 | B16: Retail sales | C16: Retail Sales | D16: Two Nykaa names: 'Nykaa Fashion' (900 lines) and 'Nykaa' (34 lines) | E16: Payment modes 'Prepaid - Nykaa Fashion' and 'Prepaid - Nykaa' | F16: Nykaa split across two channels | G16: Proposed: one channel 'Nykaa' with the two names kept as sub-channels | H16: Assumed - please confirm | J16: Low | K16: Business (you)
A17: D-016 | B17: Retail sales | C17: Retail Sales | D17: 144 Jaipur Branch rows have a blank payment mode | E17: All at '08 Jaipur Branch' | F17: Payment-type analysis incomplete | G17: Channel comes from CONTACTNAME, so not blocking | H17: Handled in model | J17: Low | K17: ERP team
A18: D-017 | B18: Retail sales | C18: Retail Sales | D18: Almost no returns inside the sales file | E18: Only 19 credit notes in 25,899 lines | F18: Returns under-counted | G18: Returns loaded from the dedicated return registers | H18: Resolved (business confirmed) | I18: Return data sheets provided | J18: High | K18: Data team
A19: D-018 | B19: Retail sales | C19: Retail Sales, WMS | D19: Customer personal data (names, phones, emails, addresses) | E19: Present in Retail Sales and WMS dispatch | F19: Privacy and compliance risk | G19: PII stays only in the restricted raw layer; core and mart hold pincode/city/state only | H19: Handled in model | J19: High | K19: Data team
A20: D-019 | B20: Domestic sales | C20: Domestic Sales | D20: CONTACTNAME mixes B2B, franchise, SIS, quick commerce, group exports and employees | E20: 117 distinct accounts in the sample | F20: Sale-or-return stock counted as final revenue | G20: Separate partner types; B2B = final, franchise/SIS/QC = sale-or-return | H20: Open - business | I20: Rules confirmed. Billing names of franchise, SIS and QC partners still to be supplied | J20: High | K20: Business (you)
A21: D-020 | B21: Domestic sales | C21: Domestic Sales | D21: Invoices to Dileep group companies | E21: 54 lines, 15 bills, Rs 21.4 lakh (7.75% of domestic taxable), mostly Dileep Crafts | F21: Related-party sales inflate revenue and distort margin | G21: Partner type GROUP_EXPORT: exports at cost, shown as own channel | H21: Resolved (business confirmed) | I21: Exports go through Dileep, billed cost-to-cost | J21: High | K21: Data team
A22: D-021 | B22: Domestic sales | C22: Domestic Sales | D22: Low unit prices on Dileep Industries and Dileep Jewellery bills | E22: Rs 5-25 per unit, no discount (e.g. 280 units for Rs 1,606) | F22: Could look like data errors | G22: Kept as recorded | H22: Resolved (business confirmed) | I22: These are cost prices | J22: Low | K22: Data team
A23: D-022 | B23: Domestic sales | C23: Domestic Sales | D23: CORRECTION: earlier example (price 1,855.93, discount 1,855.09, taxable 0.84) was an Ayush Baid (employee) line, NOT a Dileep bill | E23: Checked: only 2 Dileep lines have a near-100% discount (Sampling Unit Rs 0.97, Potteries Rs 0.96) | F23: Wrong conclusion about Dileep pricing | G23: Record corrected | H23: Resolved (business confirmed) | I23: Corrected in this log | J23: Low | K23: Data team
A24: D-023 | B24: Domestic sales | C24: Domestic Sales | D24: Lines billed at normal price with a 99-100% discount (near-free) | E24: 106 lines, 60 bills, Rs 63 total: Ayush Baid 42, Sundry Customer 22, Tanishq/Titan 14, others | F24: Free units counted as sold: demand inflated for Stock AI; B2B sample units counted as B2B sales | G24: Proposed: flag lines with >=99% discount as 'free / sample issue' and exclude them from demand | H24: Open - business | I24: Are these samples / free issues? | J24: High | K24: Business (you)
A25: D-024 | B25: Domestic sales | C25: Domestic Sales | D25: 'Sundry Customer' is a catch-all account | E25: 171 lines, 21 bills, Rs 4,960 taxable; products incl. cake stand, paper bags, tissue, gift cards | F25: Default rule would treat it as an EMPLOYEE (not on business list) | G25: Held as UNCLASSIFIED until answered | H25: Open - business | I25: What is Sundry Customer (walk-in / cash B2B / misc)? | J25: Medium | K25: Business (you)
A26: D-025 | B26: Domestic sales | C26: Domestic Sales | D26: 209 lines have a blank Taxable value | E26: Mostly carry bags (COCB04-11); 146 on Sundry Customer; Net Amount is present on all of them | F26: Revenue lost for these lines if Taxable used blindly | G26: Proposed: Taxable = Net Amount - Total Tax (relationship holds on 100% of other lines), flagged as derived | H26: Handled in model | J26: Medium | K26: Data team
A27: D-026 | B27: Domestic sales | C27: Domestic Sales | D27: Net Amount INCLUDES GST | E27: Taxable + Total Tax = Net Amount on 100% of 5,042 lines | F27: Revenue overstated if Net Amount used | G27: Headline value = Taxable | H27: Resolved (business confirmed) | I27: Headline sales = excluding GST | J27: High | K27: Data team
A28: D-027 | B28: Domestic sales | C28: Domestic Sales | D28: Direct export rows to Singapore, although exports are said to go through Dileep | E28: 2 lines to 'Hindustan Exports', Rs 1 each | F28: Unclear classification | G28: Held as EXPORT_CUSTOMER; Rs 1 lines also fall under the near-free issue | H28: Open - business | I28: Are these samples to an exporter? | J28: Low | K28: Business (you)
A29: D-028 | B29: Domestic sales | C29: Domestic Sales | D29: Person names are employees taking exhibition stock | E29: e.g. Ayush Baid, Riya Sharma | F29: Internal movement counted as B2B sales | G29: Unlisted names = EMPLOYEE by rule; each load reports names classified this way | H29: Resolved (business confirmed) | I29: Any person's name is an employee; no list needed | J29: High | K29: Data team
A30: D-029 | B30: Returns | C30: Retail Sales Return | D30: FBA-named contacts in retail returns | E30: e.g. 'Dileep Essentials Pvt Ltd FBA DED4' | F30: Could be mistaken for internal transfers | G30: Genuine customer returns, received at that FBA warehouse | H30: Resolved (business confirmed) | I30: Customer returns going back to FBA | J30: Medium | K30: Data team
A31: D-030 | B31: Returns | C31: Domestic Sale Return | D31: Person names in domestic returns | E31: e.g. Riya Sharma-Customer, Ayush Baid | F31: Counted as B2B returns | G31: EMPLOYEE by rule; excluded from return-rate metrics | H31: Resolved (business confirmed) | I31: Employees returning exhibition stock | J31: Medium | K31: Data team
A32: D-031 | B32: Returns | C32: Domestic Sale Return | D32: Kiranakart Technologies (Blinkit) appears in domestic returns | E32: Returns found in the domestic return register | F32: Could look misplaced | G32: Unsold stock back from a sale-or-return partner | H32: Resolved (business confirmed) | I32: Blinkit returns unsold stock | J32: Medium | K32: Data team
A33: D-032 | B33: Returns | C33: Domestic Sale Return | D33: Return date field holds several dates joined by ';' | E33: CORRECTED: first read as the same date repeated. Loader found they can DIFFER (437 rows in FY25-26, e.g. '22/11/2024;22/01/2025'); see the goods-receipt issue below | F33: Dates fail to parse or pick the wrong day | G33: Raw keeps the text unchanged; handled with the goods-receipt issue | H33: Handled in model | J33: Medium | K33: Data team
A34: D-033 | B34: Returns | C34: Return files | D34: Return date column name differs by file | E34: Retail: RETURNDATE; Domestic: RTNFROMCUSTDT | F34: Wrong column picked | G34: Mapped explicitly per source | H34: Handled in model | J34: Low | K34: Data team
A35: D-034 | B35: Returns | C35: Retail Sales Return | D35: ~7% of retail returns don't match a sale in the sample | E35: 2,875 of 3,089 bills matched | F35: Returns without their original sale | G35: Expected (sales before Apr 2026); re-check on full data | H35: Open - verify with full data | J35: Low | K35: Data team
A36: D-035 | B36: Returns | C36: Retail Sales Return | D36: Shipping-charge reversal lines in returns | E36: 287 rows with PRODNUM 'SHIPPING R' | F36: Returned 'units' of a non-product | G36: CHARGE item type; excluded from product returns | H36: Handled in model | J36: Low | K36: Data team
A37: D-036 | B37: Returns | C37: Domestic Sale Return | D37: Domestic returns have no clear link to the original invoice | E37: BILLNUM here is the credit note; RTNFROMCUST is the goods receipt | F37: Cannot compute return rate per original B2B invoice | G37: Original bill kept nullable | H37: Open - ERP team | I37: Is the original invoice number stored anywhere in this report? | J37: Low | K37: ERP team
A38: D-037 | B38: Returns | C38: WMS, Returns | D38: RTO (failed delivery) vs customer return after delivery | E38: RTO seen in WMS status; customer returns in return registers | F38: Returns mixed or missed | G38: Both kept, as separate events | H38: Resolved (business confirmed) | I38: Return registers provided | J38: Medium | K38: Data team
A39: D-038 | B39: Stock transfers | C39: Stock Transfer, Inward | D39: Sending / receiving location only encoded in the document number prefix | E39: Prefixes JPR/, THA/, HYD, BAG/, AMD ... ; no location column | F39: Stock movements assigned to the wrong place when a new prefix appears | G39: Interim prefix-to-location table (ref.document_prefix_location) | H39: Open - ERP team | I39: Add a branch / location column to transfer and return exports | J39: High | K39: ERP team
A40: D-039 | B40: Stock transfers | C40: Stock Transfer, Inward | D40: Outward stock never received | E40: 31 of 622 outward documents wholly unreceived = 2,311 units (233 from Jun, 34 from May). CORRECTED total counting SKU lines, incl. partly received documents: 2,794 units in transit (built warehouse, verified independently) | F40: Stock can disappear between locations | G40: In-transit view in mart; age of unreceived transfers reported | H40: Open - ERP team | I40: Why are May/June transfers still unreceived? Are FBA receipts recorded in the ERP? | J40: Medium | K40: ERP team
A41: D-040 | B41: Stock transfers | C41: Stock Transfer Inward | D41: Same document + SKU appears twice | E41: 2 duplicate DOCNUM + PRODNUM pairs | F41: Real lines rejected as duplicates | G41: Line-occurrence counter in the key | H41: Handled in model | J41: Low | K41: Data team
A42: D-041 | B42: Stock transfers | C42: Stock Transfer | D42: Outward quantities are negative | E42: All outward PRODTRANSQTY < 0 | F42: Signs double-flipped in sums | G42: Stored positive with a direction column | H42: Handled in model | J42: Low | K42: Data team
A43: D-042 | B43: Stock transfers | C43: Stock Transfer, Inward | D43: Product hierarchy fields empty | E43: PRODGROUPNAME, PRODBRANDNAME, PRODMODEL, DEPARTMENTNAME 100% blank | F43: No category from these files | G43: Product attributes taken from other sources | H43: Handled in model | J43: Low | K43: Data team
A44: D-043 | B44: Stock transfers | C44: All files | D44: Same location spelled differently across files | E44: '24 FBA WH - AMD2' vs 'Dileep Essentials Pvt Ltd Ahmedabad FBA AMD2' | F44: Joins by location fail | G44: One location code with every spelling mapped (ref.location_alias) | H44: Handled in model | I44: Mapping to be reviewed line by line (next step) | J44: High | K44: Data team
A45: D-044 | B45: Purchase orders | C45: Pending PO | D45: PO report contains return invoices, not only purchases | E45: Companies and own stores sending stock back raise invoices here | F45: Returns counted as purchases; lead time wrong | G45: Any counterparty not on the factory list = return-inward | H45: Open - business | I45: Rule confirmed; factory list to be supplied | J45: High | K45: Business (you)
A46: D-045 | B46: Purchase orders | C46: Pending PO | D46: Shoppers Stop appears as a PO counterparty | E46: 'Shoppers Stop Limited-Vendor', 356 rows | F46: Customer mistaken for supplier | G46: Return-inward by rule | H46: Resolved (business confirmed) | I46: Returns raise an invoice in the PO list | J46: Medium | K46: Data team
A47: D-046 | B47: Purchase orders | C47: Pending PO | D47: Returned-to-supplier fields rarely filled | E47: Returned Qty / Value on 27 of 1,350 rows | F47: Supplier return rate looks lower than reality | G47: Kept as reported | H47: Handled in model | J47: Low | K47: Data team
A48: D-047 | B48: Purchase orders | C48: Pending PO | D48: CORRECTED: one GRN per PO line was assumed; part deliveries list several receipts in ONE cell | E48: Found by the first transform run: 47 PO lines list 155 receipts in GRNNUM (e.g. 'JPR/GRN/199;305;89') with one date and one total quantity. The loader's uniqueness check could not catch it: it is one cell, not several rows | F48: Per-receipt dates and quantities unknown; supplier lead time approximate for those lines | G48: Receipt table = one row per PO line as reported, receipt numbers in a bridge, lines flagged approximate. Nothing split by guesswork | H48: Open - ERP team | I48: Can the ERP export a GRN register (one row per receipt with its own date and quantity)? Gap G-027 | J48: Medium | K48: ERP team
A49: D-048 | B49: Inventory | C49: Inventory report (.xls) | D49: Stock report is a wide pivot, not a table | E49: 38 location blocks of Qty + MRP side by side; 19 header rows | F49: Hard to load; easy to misalign columns | G49: Loader unpivots to SKU x location and checks block headers | H49: Handled in model | J49: Medium | K49: Data team
A50: D-049 | B50: Inventory | C50: Inventory report (.xls) | D50: Report includes non-sellable items | E50: Trading 4,020; Packaging 87; Accessory 49; Stores & Consumables 6 | F50: Stock value and SKU counts polluted | G50: Only TRADING items count as SKUs | H50: Resolved (business confirmed) | I50: Only Trading are SKUs | J50: Medium | K50: Data team
A51: D-050 | B51: Inventory | C51: Inventory, Blinkit inventory | D51: Same Blinkit stock reported by the ERP and by Blinkit | E51: '27 Blinkit - Pune P2' (ERP) and 'Pune P2 - Feeder' (Blinkit) | F51: Stock double-counted | G51: Both kept; each location counted once from its system of record | H51: Open - business | I51: Which is the truth for Blinkit locations: ERP or Blinkit's report? | J51: Medium | K51: Business (you)
A52: D-051 | B52: Inventory | C52: Blinkit inventory | D52: Negative 'Net scheduled inventory' values | E52: e.g. -92, -125 | F52: Wrong stock at Blinkit | G52: Stored; excluded from all stock metrics | H52: Open - business | I52: Being confirmed with Blinkit | J52: Medium | K52: Business (you)
A53: D-052 | B53: Inventory | C53: Amazon FBA | D53: Amazon's own FBA inventory report not provided | E53: FBA stock known only from the ERP | F53: ERP and Amazon may disagree (see unreceived FBA transfers) | G53: FBA locations use ERP until an Amazon report is added | H53: Open - business | I53: Can the Amazon FBA inventory report be exported? | J53: Medium | K53: Business (you)
A54: D-053 | B54: Inventory | C54: Inventory report (.xls) | D54: Product category blank in the stock report | E54: Prod Group / Category columns empty | F54: No category on stock views | G54: Category from sales and PO files | H54: Handled in model | J54: Low | K54: Data team
A55: D-054 | B55: Product master | C55: Final Master | D55: Which SKUs are currently sold | E55: 472 Continued, 3,548 Discontinued | F55: Stock AI recommends discontinued SKUs | G55: Lifecycle status from Final Master; discontinued excluded from replenishment | H55: Resolved (business confirmed) | I55: Final Master is the list of current SKUs | J55: High | K55: Data team
A56: D-055 | B56: Product master | C56: Final Master | D56: How current the master's status is | F56: Stale status = wrong replenishment | G56: Fresh copy with every data pull; changes kept in product history | H56: Resolved (business confirmed) | I56: Updated whenever something changes | J56: Medium | K56: Data team
A57: D-056 | B57: Product master | C57: Final Master | D57: Only Sheet1 is structured | E57: Other sheets: Mastor Jan 2026, MRP to change Lot 1/2 | F57: Working sheets loaded as data | G57: Only Sheet1 loaded | H57: Handled in model | J57: Low | K57: Data team
A58: D-057 | B58: WMS dispatch | C58: WMS dispatch | D58: CORRECTION: channel is in 'Site Location', not 'Customer' (earlier misread) | E58: Customer column = placeholder 999999 | F58: Channel from the wrong column | G58: Channel from Site Location | H58: Resolved (business confirmed) | I58: Corrected | J58: Medium | K58: Data team
A59: D-058 | B59: WMS dispatch | C59: WMS dispatch | D59: Which warehouse 'Warehouse' means | E59: Order Serving Location = 'Warehouse' on every row | F59: Fulfilment location unknown | G59: All shipments = Bagru warehouse | H59: Resolved (business confirmed) | I59: B2C only, all from Bagru | J59: Medium | K59: Data team
A60: D-059 | B60: WMS dispatch | C60: WMS dispatch | D60: Several SKUs in one cell with one combined quantity | E60: e.g. 'SWTEA1766 , WDSWA2926' with Delivery Qty 2 | F60: Per-SKU quantities unknown | G60: Bridge table; per-SKU qty from the matching ERP invoice line, else left empty | H60: Open - verify with full data | I60: Invoice match rate to be checked on the full export | J60: Medium | K60: Data team
A61: D-060 | B61: WMS dispatch | C61: WMS dispatch | D61: Long numbers exported in scientific notation | E61: Ext Manifest No '1.60396E+13' | F61: Digits permanently lost; IDs don't match | G61: All IDs loaded as text | H61: Open - ERP team | I61: Export IDs as text or the report as CSV | J61: Medium | K61: ERP team
A62: D-061 | B62: WMS dispatch | C62: WMS dispatch | D62: Dates in month/day order | E62: e.g. 4/14/2025 | F62: Day and month swapped for dates up to the 12th | G62: Date format declared per source | H62: Handled in model | J62: High | K62: Data team
A63: D-062 | B63: WMS dispatch | C63: WMS dispatch | D63: Status values in mixed case | E63: 'Shipped', 'delivered', 'RTO Delivered' | F63: Groupings split | G63: Standardised via ref.code_mapping | H63: Handled in model | J63: Low | K63: Data team
A64: D-063 | B64: WMS dispatch | C64: WMS dispatch | D64: Placeholder customer contacts | E64: 9999999999, dummy@nykaa.com, 'No Address Provided' | F64: Fake data in customer analysis | G64: PII not used in core | H64: Handled in model | J64: Low | K64: Data team
A65: D-064 | B65: Quick commerce | C65: Blinkit sales | D65: Which Blinkit order statuses count as sold | E65: Sample has 8 rows, all DELIVERED | F65: Demand inflated by cancelled orders | G65: Only DELIVERED counted | H65: Resolved (business confirmed) | I65: Delivered = sold | J65: Medium | K65: Data team
A66: D-065 | B66: Quick commerce | C66: Blinkit sales | D66: No store id in the Blinkit sales export | E66: Only supply / customer city | F66: No store-level demand | G66: Grain uses supply city in place of store | H66: Handled in model | J66: Low | K66: Data team
A67: D-066 | B67: Quick commerce | C67: Instamart sales | D67: Brand Metrics sheet is marketing data | E67: City-level metrics, not sales lines | G67: Not loaded in this phase | H67: Handled in model | J67: Low | K67: Data team
A68: D-067 | B68: Locations | C68: Inventory, Transfers | D68: Bagru warehouse naming across files | E68: '08 Jaipur Branch' = Bagru warehouse (confirmed). Bare 'Dileep Essentials Pvt Ltd' is the same place: it is billed at 08 Jaipur Branch and uses the JPR/ transfer prefixes | F68: Bagru stock split across names | G68: All three names mapped to one location, BAGRU_WH | H68: Resolved (business confirmed) | I68: 08 Jaipur Branch = Bagru warehouse | J68: Medium | K68: Data team
A69: D-068 | B69: Locations | C69: All | D69: Head office location | E69: Standalone 'Dileep Essentials Pvt Ltd' / HO | G69: HEAD_OFFICE location in Bagru | H69: Resolved (business confirmed) | I69: HO is in Bagru | J69: Low | K69: Data team
A70: D-069 | B70: General | C70: All | D70: Currency and timezone never explicitly confirmed | E70: All data appears Indian (INR, IST) | F70: Wrong if any foreign-currency data exists | G70: INR and IST stored as settings | H70: Assumed - please confirm | J70: Low | K70: Business (you)
A71: D-070 | B71: Inventory | C71: Inventory report (.xls) | D71: The stock report has a 'Total' column that is the sum of all locations | E71: Equals the sum of the 37 location columns on 100% of rows | F71: All stock counted twice if loaded as a location | G71: Loader skips the Total block and uses it only to check the unpivot is complete | H71: Handled in model | J71: High | K71: Data team
A72: D-071 | B72: Locations | C72: Inventory report (.xls) | D72: 13 ERP locations hold zero stock, incl. 7 stores with no retail invoices | E72: Stores: GK Store, Indiranagar, VR Mall, Infiniti Malad, SIB Bandra, Goa Anjuna, CG Road. Also DEPL Delhi / Lucknow / Mumbai PPOB and FBA BLR5, NAG1, DED5 | F72: Closed locations clutter reports; stock appearing there later goes unnoticed | G72: Proposed inactive; any stock or sale at an inactive location raises a warning | H72: Assumed - please confirm | I72: See 'Open questions' in Reference_Mappings_Draft_v1 | J72: Medium | K72: Business (you)
A73: D-072 | B73: Locations | C73: Stock transfers | D73: 'Dileep Essentials Pvt Ltd Bagru' is a different location from the Bagru warehouse | E73: Uses transfer prefix BAG/ (2 documents); the Bagru warehouse uses JPR/ | F73: Stock moved to / from it assigned to the wrong place | G73: Left unmapped (goes to Unknown) until answered | H73: Open - business | I73: Is it '08 Bagru Popup'? | J73: Medium | K73: Business (you)
A74: D-073 | B74: Locations | C74: Inventory report (.xls) | D74: '08 Essential - DFAL' holds stock but its purpose is unknown | E74: 688 units of 15 SKUs; transfer prefixes IS/DF and RC/DF | F74: Stock counted as sellable when it may not be | G74: Proposed not sellable until confirmed | H74: Open - business | I74: What is DFAL, and is its stock sellable? | J74: Medium | K74: Business (you)
A75: D-074 | B75: Locations | C75: Inventory report (.xls) | D75: Jaipur Meeraki holds stock but has no retail invoices | E75: 145 units; no Retail Sales rows Apr-Sep 2026 | F75: Store type unclear (own / SIS / franchise) | G75: Proposed own store | H75: Open - business | I75: What kind of store is Meeraki? | J75: Low | K75: Business (you)
A76: D-075 | B76: Locations | C76: Retail Sales Return (FY25-26) | D76: Two store names don't match any ERP location | E76: 'Dileep Essentials Pvt Ltd Jaipur Store' (7 returns) and 'Dileep Essentials Pvt Ltd Lucknow' | F76: Returns received at an unknown location | G76: Left unmapped until answered | H76: Open - business | I76: Which locations are these? | J76: Low | K76: Business (you)
A77: D-076 | B77: Retail sales | C77: Retail Sales Return (FY25-26) | D77: Channels seen only in last year's returns | E77: 'Flipkart Website', 'Ellementry International', and Blinkit Mumbai / Pune contacts | F77: Channel list incomplete for FY25-26 | G77: Flipkart and Blinkit mapped (proposed); Ellementry International left unmapped | H77: Open - business | I77: Which channel is 'Ellementry International'? | J77: Low | K77: Business (you)
A78: D-077 | B78: Returns | C78: Domestic Sale Return | D78: One credit note can cover several goods receipts with different dates | E78: RTNFROMCUST lists receipts ('JPR/GIR/3923;5011;5012') and RTNFROMCUSTDT their dates in the same order; e.g. credit note of 29-Oct-2025 for goods received 22-Nov-2024 and 22-Jan-2025 | F78: 'Return date' is ambiguous: sales reversal (credit note date) vs stock back in hand (receipt date) | G78: Credit-note date (BILLDATE) for net sales; receipt dates for stock timing; each receipt stored separately (bridge_return_goods_receipt) | H78: Resolved (business confirmed) | I78: Approved with Target Data Model v2 (1 Oct 2026): rule BR-023 | J78: High | K78: Data team
A79: D-078 | B79: Returns | C79: Domestic Sale Return | D79: Receipt date list shorter than the receipt list on some credit notes | E79: e.g. 3 receipts with 2 dates; 100 receipts in the sample cannot be paired with a date | F79: Wrong receipt dates if paired by position | G79: Unpaired receipts left out of the receipts bridge; the return uses only the dates given | H79: Open - ERP team | I79: Why does the ERP drop a date when several receipts share one credit note? | J79: Low | K79: ERP team
A80: D-079 | B80: Returns | C80: Domestic Sale Return | D80: A return 'reason' column exists but is never filled | E80: Empty on all 5,924 rows | F80: Return reasons unknown, though the ERP can hold them | G80: Reason dimension ready; reasons load as soon as the field is filled | H80: Open - business | I80: Can the team start filling the reason when raising a credit note? Gap G-009 | J80: Medium | K80: Business (you)
A81: D-080 | B81: Inventory | C81: Built warehouse (stock view) | D81: Stock at sale-or-return partners has no opening balance | E81: Blinkit consignment location shows -5,749 units: Kiranakart returned stock in the period that was invoiced to it before the data starts; Blinkit net sales -Rs 2.44 lakh for the same reason | F81: Partner stock understated, even negative, on dashboards | G81: The stock view labels these balances 'LEDGER: no opening balance'; nothing is clamped or hidden | H81: Open - business | I81: Can each franchise, SIS and quick-commerce partner state the stock it held on 1-Apr-2025? Gap G-028 | J81: High | K81: Business (you)
A82: D-081 | B82: Quick commerce | C82: Instamart sales and inventory | D82: Instamart's 'Elle SKU' shows Excel's N/A lookup error where its lookup failed | E82: 4 sales rows, 6 inventory rows | F82: An Excel error was briefly created as a product | G82: Excel error values are treated as 'no SKU': rows go to Unknown and are counted | H82: Handled in model | J82: Low | K82: Data team
A83: D-082 | B83: Returns | C83: Domestic Sale Return | D83: Return date column mixes real Excel dates and typed text | E83: ~90% Excel date cells, ~10% typed text 'dd/mm/yyyy;...' | F83: Only one of the two forms parsed | G83: Loader stores Excel dates as ISO text and keeps typed text unchanged; staging parses both | H83: Handled in model | J83: Medium | K83: Data team
A84: D-083 | B84: Purchase orders | C84: Pending PO | D84: The PO export's real date is unknown | E84: File name says '12_09' but it has 77 POs opened after 12-Sep, the latest on 24-Sep, and receipts to 24-Sep | F84: PO state recorded against the wrong date; pending-PO view wrong | G84: Loader refuses a PO file whose as-of date is earlier than dates inside it | H84: Open - business | I84: On what date was this PO report exported? Please note the export date for every future PO pull | J84: Medium | K84: Business (you)
A85: D-084 | B85: Scope | C85: Blinkit / Instamart inventory, Final Master, PO | D85: These exports carry no date of their own | E85: File names give month only (e.g. 'sep_26') or an unclear code | F85: Snapshot loaded against the wrong day | G85: Loader requires --as-of for every snapshot, state or master file | H85: Handled in model | I85: When saving these exports, put the full export date in the file name | J85: Medium | K85: Business (you)
A86: D-085 | B86: Inventory | C86: Inventory report (.xls) | D86: 7 locations are selected in the report filter but have no column | E86: Head Office, 08 Repair and Damage, 08 Offline - WH, 07 FBA WH - DED1, 27 FBA WH - ISK3, 08 Jaipur - Mansarovar, 29 FBA WH - BLX9. 13 other zero-stock locations DO get a column | F86: Stock at these locations (e.g. damaged stock) may be missing from the report | G86: Loader compares filter vs columns on every load and records a warning; locations added to the mapping as proposals | H86: Open - ERP team | I86: Why do these 7 have no column? Does Repair and Damage hold stock? | J86: Medium | K86: ERP team
A87: D-086 | B87: Inventory | C87: Inventory report (.xls) | D87: Report ends with a grand-total row | E87: Per-location totals in Indian number format, e.g. '1,12,92,483.18' | F87: Footer loaded as a product row | G87: Every location column must add up to its footer total, and every row to its Total column, or the whole file is rejected | H87: Handled in model | J87: Medium | K87: Data team
A88: D-087 | B88: Product master | C88: Final Master | D88: Sheet1 also contains a full copy of stock columns | E88: After Prod Num/Status/Name/Type/Unit come stock blocks laid out like the stock report | F88: Stale stock read as current inventory | G88: Only the 5 product columns are loaded; the stock copy is ignored by design | H88: Handled in model | J88: Medium | K88: Data team
A89: D-088 | B89: Quick commerce | C89: Instamart sales, Blinkit inventory | D89: Columns without a header | E89: Instamart: a 0,1,2... row counter; Blinkit: every value '--' | F89: Real data dropped if an unnamed column ever holds some | G89: Dropped only after checking they are exactly a counter / only '--'; otherwise the file is rejected | H89: Handled in model | J89: Low | K89: Data team
A90: D-089 | B90: Returns | C90: Pending PO, Domestic Sale Return | D90: Shoppers Stop returns appear on two routes | E90: PO report: 316 return-inward receipt lines (563 units); Domestic Sale Return: 68 credit-note lines (95 units); only 3 pairs match on SKU, quantity and date | F90: If both record the same goods, the stock ledger counts the return twice | G90: No return-inward movements are created until the factory list arrives and this is answered | H90: Open - business | I90: Are these two different return routes, or the same goods recorded twice? | J90: High | K90: Business (you)
A91: D-090 | B91: Domestic sales | C91: Domestic Sale Return (FY25-26) | D91: 'DILEEP ESSENTIALS INC' appears as a return counterparty | E91: 1 row | F91: Unclear whether it is a group export entity | G91: Listed as UNCLASSIFIED so it is never classified by elimination | H91: Open - business | I91: What is Dileep Essentials Inc? | J91: Low | K91: Business (you)
A92: D-091 | B92: Domestic sales | C92: Domestic Sales, PO | D92: Classification by elimination is unsafe until the partner list is complete | E92: Until the franchise / SIS / quick-commerce and factory names arrive, every unlisted company would become an employee (domestic) or a return-inward (PO) | F92: Real revenue silently treated as internal stock | G92: Safety switch partner_list_complete = false: unlisted names stay UNCLASSIFIED until the business confirms the list is complete | H92: Handled in model | J92: High | K92: Data team
A93: D-092 | B93: Quick commerce | C93: Domestic Sales / Returns, Stock Transfers | D93: Two possible supply routes to Blinkit | E93: Kiranakart (Blinkit) appears on domestic credit notes, while stock also reaches Blinkit feeder locations by ERP stock transfer | F93: Blinkit stock split across two pools or counted twice | G93: Kept as two locations: Blinkit consignment stock (invoiced) and the Blinkit feeder locations (transferred) | H93: Open - business | I93: Is Blinkit supplied by invoice, by stock transfer, or did it change over time? | J93: Medium | K93: Business (you)
A94: D-093 | B94: Stock transfers | C94: Stock Transfer Inward | D94: Inward prefix 'STK' is shared by two receiving locations | E94: Used for both AMD2 (20 documents) and LKO1 (1) | F94: Receipts assigned to the wrong location | G94: Receiver taken from the linked outward document, not from the prefix | H94: Handled in model | J94: Medium | K94: Data team

Sheet Legend
A1: Status | B1: Meaning
A2: Resolved (business confirmed) | B2: The business answered; the answer is applied in the model.
A3: Handled in model | B3: A data quirk the model deals with automatically; no business input needed.
A4: Open - business | B4: Waiting on an answer or data from the business.
A5: Open - ERP team | B5: Waiting on a change or answer from the ERP team.
A6: Open - verify with full data | B6: Design is ready; must be re-checked when the full 1.5-year data arrives.
A7: Assumed - please confirm | B7: The model uses a proposed rule until someone confirms or corrects it.
A9: How to update | B9: Change Status and fill 'Answer / resolution' in the Issue Log. Add new issues as new rows with the next D-number. The Summary sheet recalculates.
